Workbook

Sheet 任务清单
A1: Sakura · 工作进度管理（任务清单）—— 一行一个任务，状态自动上色、看板自动统计
A2: 日期 | B2: 星期 | C2: 部门 | D2: 负责人 | E2: 分类 | F2: 工作内容 | G2: 状态 | H2: 计划完成日 | I2: 实际完成日 | J2: 是否延期 | K2: 备注
A3: 2026-08-03 | B3: =IF(A3="","",CHOOSE(WEEKDAY(A3),"周日","周一","周二","周三","周四","周五","周六")) | C3: 日本 | D3: 小裴(财务) | E3: 财务 | F3: yomite请求书 | G3: 已完成 | H3: 2026-08-03 | I3: 2026-08-03 | J3: =IF(AND(G3<>"已完成",G3<>"",H3<>"",H3<TODAY()),"⚠️延期","")
A4: 2026-08-03 | B4: =IF(A4="","",CHOOSE(WEEKDAY(A4),"周日","周一","周二","周三","周四","周五","周六")) | C4: 日本 | D4: 小裴(财务) | E4: 财务 | F4: Q1请求书 / babubabu请求书 | G4: 已完成 | H4: 2026-08-03 | I4: 2026-08-03 | J4: =IF(AND(G4<>"已完成",G4<>"",H4<>"",H4<TODAY()),"⚠️延期","")
A5: 2026-08-11 | B5: =IF(A5="","",CHOOSE(WEEKDAY(A5),"周日","周一","周二","周三","周四","周五","周六")) | C5: 樱拓 | D5: 咩咩(贸易) | E5: 贸易 | F5: 考勤拉取 / 工资表制作 | G5: 进行中 | H5: 2026-08-12 | J5: =IF(AND(G5<>"已完成",G5<>"",H5<>"",H5<TODAY()),"⚠️延期","")
A6: 2026-08-11 | B6: =IF(A6="","",CHOOSE(WEEKDAY(A6),"周日","周一","周二","周三","周四","周五","周六")) | C6: 樱拓 | D6: 咩咩(贸易) | E6: 贸易 | F6: 预算表格制作 | G6: 未开始 | H6: 2026-08-15 | J6: =IF(AND(G6<>"已完成",G6<>"",H6<>"",H6<TODAY()),"⚠️延期","")
A7: 2026-08-17 | B7: =IF(A7="","",CHOOSE(WEEKDAY(A7),"周日","周一","周二","周三","周四","周五","周六")) | C7: 樱启 | D7: 张姐(供应链) | E7: 行政/其他 | F7: 税务申报 | G7: 进行中 | H7: 2026-08-20 | J7: =IF(AND(G7<>"已完成",G7<>"",H7<>"",H7<TODAY()),"⚠️延期","")
A8: 2026-08-30 | B8: =IF(A8="","",CHOOSE(WEEKDAY(A8),"周日","周一","周二","周三","周四","周五","周六")) | C8: 樱启 | D8: 张姐(供应链) | E8: 行政/其他 | F8: 抖音费用确认(无费用可继续保持) | G8: 未开始 | H8: 2026-08-30 | J8: =IF(AND(G8<>"已完成",G8<>"",H8<>"",H8<TODAY()),"⚠️延期","")
B9: =IF(A9="","",CHOOSE(WEEKDAY(A9),"周日","周一","周二","周三","周四","周五","周六")) | J9: =IF(AND(G9<>"已完成",G9<>"",H9<>"",H9<TODAY()),"⚠️延期","")
B10: =IF(A10="","",CHOOSE(WEEKDAY(A10),"周日","周一","周二","周三","周四","周五","周六")) | J10: =IF(AND(G10<>"已完成",G10<>"",H10<>"",H10<TODAY()),"⚠️延期","")
B11: =IF(A11="","",CHOOSE(WEEKDAY(A11),"周日","周一","周二","周三","周四","周五","周六")) | J11: =IF(AND(G11<>"已完成",G11<>"",H11<>"",H11<TODAY()),"⚠️延期","")
B12: =IF(A12="","",CHOOSE(WEEKDAY(A12),"周日","周一","周二","周三","周四","周五","周六")) | J12: =IF(AND(G12<>"已完成",G12<>"",H12<>"",H12<TODAY()),"⚠️延期","")
B13: =IF(A13="","",CHOOSE(WEEKDAY(A13),"周日","周一","周二","周三","周四","周五","周六")) | J13: =IF(AND(G13<>"已完成",G13<>"",H13<>"",H13<TODAY()),"⚠️延期","")
B14: =IF(A14="","",CHOOSE(WEEKDAY(A14),"周日","周一","周二","周三","周四","周五","周六")) | J14: =IF(AND(G14<>"已完成",G14<>"",H14<>"",H14<TODAY()),"⚠️延期","")
B15: =IF(A15="","",CHOOSE(WEEKDAY(A15),"周日","周一","周二","周三","周四","周五","周六")) | J15: =IF(AND(G15<>"已完成",G15<>"",H15<>"",H15<TODAY()),"⚠️延期","")
B16: =IF(A16="","",CHOOSE(WEEKDAY(A16),"周日","周一","周二","周三","周四","周五","周六")) | J16: =IF(AND(G16<>"已完成",G16<>"",H16<>"",H16<TODAY()),"⚠️延期","")
B17: =IF(A17="","",CHOOSE(WEEKDAY(A17),"周日","周一","周二","周三","周四","周五","周六")) | J17: =IF(AND(G17<>"已完成",G17<>"",H17<>"",H17<TODAY()),"⚠️延期","")
B18: =IF(A18="","",CHOOSE(WEEKDAY(A18),"周日","周一","周二","周三","周四","周五","周六")) | J18: =IF(AND(G18<>"已完成",G18<>"",H18<>"",H18<TODAY()),"⚠️延期","")
B19: =IF(A19="","",CHOOSE(WEEKDAY(A19),"周日","周一","周二","周三","周四","周五","周六")) | J19: =IF(AND(G19<>"已完成",G19<>"",H19<>"",H19<TODAY()),"⚠️延期","")
B20: =IF(A20="","",CHOOSE(WEEKDAY(A20),"周日","周一","周二","周三","周四","周五","周六")) | J20: =IF(AND(G20<>"已完成",G20<>"",H20<>"",H20<TODAY()),"⚠️延期","")
... B122: =IF(A122="","",CHOOSE(WEEKDAY(A122),"周日","周一","周二","周三","周四","周五","周六")) | J122: =IF(AND(G122<>"已完成",G122<>"",H122<>"",H122<TODAY()),"⚠️延期","")

Sheet 进度看板
A1: Sakura · 工作进度看板（自动汇总）
A2: 任务清单填完自动更新；如未刷新按 F9 / 重开。今天： | E2: =TODAY()
A4: 总任务数 | B4: =COUNTA(任务清单!$F$3:$F$122)
A5: 已完成 | B5: =COUNTIF(任务清单!$G$3:$G$122,"已完成")
A6: 进行中 | B6: =COUNTIF(任务清单!$G$3:$G$122,"进行中")
A7: 未开始 | B7: =COUNTIF(任务清单!$G$3:$G$122,"未开始")
A8: 已延期 | B8: =COUNTIF(任务清单!$G$3:$G$122,"已延期")+COUNTIF(任务清单!$J$3:$J$122,"⚠️延期")
A9: 搁置 | B9: =COUNTIF(任务清单!$G$3:$G$122,"搁置")
A11: 总体完成率 | B11: =IFERROR(B5/B4,0)
A14: 按负责人 · 完成情况
A15: 负责人 | B15: 总数 | C15: 已完成 | D15: 进行中 | E15: 未完成 | F15: 完成率
A16: 小裴(财务) | B16: =COUNTIF(任务清单!$D$3:$D$122,"小裴(财务)") | C16: =COUNTIFS(任务清单!$D$3:$D$122,"小裴(财务)",任务清单!$G$3:$G$122,"已完成") | D16: =COUNTIFS(任务清单!$D$3:$D$122,"小裴(财务)",任务清单!$G$3:$G$122,"进行中") | E16: =B16-C16 | F16: =IFERROR(C16/B16,"")
A17: 咩咩(贸易) | B17: =COUNTIF(任务清单!$D$3:$D$122,"咩咩(贸易)") | C17: =COUNTIFS(任务清单!$D$3:$D$122,"咩咩(贸易)",任务清单!$G$3:$G$122,"已完成") | D17: =COUNTIFS(任务清单!$D$3:$D$122,"咩咩(贸易)",任务清单!$G$3:$G$122,"进行中") | E17: =B17-C17 | F17: =IFERROR(C17/B17,"")
A18: 张姐(供应链) | B18: =COUNTIF(任务清单!$D$3:$D$122,"张姐(供应链)") | C18: =COUNTIFS(任务清单!$D$3:$D$122,"张姐(供应链)",任务清单!$G$3:$G$122,"已完成") | D18: =COUNTIFS(任务清单!$D$3:$D$122,"张姐(供应链)",任务清单!$G$3:$G$122,"进行中") | E18: =B18-C18 | F18: =IFERROR(C18/B18,"")
A19: 毛毛(小红书) | B19: =COUNTIF(任务清单!$D$3:$D$122,"毛毛(小红书)") | C19: =COUNTIFS(任务清单!$D$3:$D$122,"毛毛(小红书)",任务清单!$G$3:$G$122,"已完成") | D19: =COUNTIFS(任务清单!$D$3:$D$122,"毛毛(小红书)",任务清单!$G$3:$G$122,"进行中") | E19: =B19-C19 | F19: =IFERROR(C19/B19,"")
A20: Alice(小红书) | B20: =COUNTIF(任务清单!$D$3:$D$122,"Alice(小红书)") | C20: =COUNTIFS(任务清单!$D$3:$D$122,"Alice(小红书)",任务清单!$G$3:$G$122,"已完成") | D20: =COUNTIFS(任务清单!$D$3:$D$122,"Alice(小红书)",任务清单!$G$3:$G$122,"进行中") | E20: =B20-C20 | F20: =IFERROR(C20/B20,"")
A21: 柚子(小红书) | B21: =COUNTIF(任务清单!$D$3:$D$122,"柚子(小红书)") | C21: =COUNTIFS(任务清单!$D$3:$D$122,"柚子(小红书)",任务清单!$G$3:$G$122,"已完成") | D21: =COUNTIFS(任务清单!$D$3:$D$122,"柚子(小红书)",任务清单!$G$3:$G$122,"进行中") | E21: =B21-C21 | F21: =IFERROR(C21/B21,"")
A22: 其他 | B22: =COUNTIF(任务清单!$D$3:$D$122,"其他") | C22: =COUNTIFS(任务清单!$D$3:$D$122,"其他",任务清单!$G$3:$G$122,"已完成") | D22: =COUNTIFS(任务清单!$D$3:$D$122,"其他",任务清单!$G$3:$G$122,"进行中") | E22: =B22-C22 | F22: =IFERROR(C22/B22,"")
A24: 按部门 · 完成情况
A25: 负责人 | B25: 总数 | C25: 已完成 | D25: 进行中 | E25: 未完成 | F25: 完成率
A26: 日本 | B26: =COUNTIF(任务清单!$C$3:$C$122,"日本") | C26: =COUNTIFS(任务清单!$C$3:$C$122,"日本",任务清单!$G$3:$G$122,"已完成") | D26: =COUNTIFS(任务清单!$C$3:$C$122,"日本",任务清单!$G$3:$G$122,"进行中") | E26: =B26-C26 | F26: =IFERROR(C26/B26,"")
A27: 樱拓 | B27: =COUNTIF(任务清单!$C$3:$C$122,"樱拓") | C27: =COUNTIFS(任务清单!$C$3:$C$122,"樱拓",任务清单!$G$3:$G$122,"已完成") | D27: =COUNTIFS(任务清单!$C$3:$C$122,"樱拓",任务清单!$G$3:$G$122,"进行中") | E27: =B27-C27 | F27: =IFERROR(C27/B27,"")
A28: 樱启 | B28: =COUNTIF(任务清单!$C$3:$C$122,"樱启") | C28: =COUNTIFS(任务清单!$C$3:$C$122,"樱启",任务清单!$G$3:$G$122,"已完成") | D28: =COUNTIFS(任务清单!$C$3:$C$122,"樱启",任务清单!$G$3:$G$122,"进行中") | E28: =B28-C28 | F28: =IFERROR(C28/B28,"")
A29: 其他 | B29: =COUNTIF(任务清单!$C$3:$C$122,"其他") | C29: =COUNTIFS(任务清单!$C$3:$C$122,"其他",任务清单!$G$3:$G$122,"已完成") | D29: =COUNTIFS(任务清单!$C$3:$C$122,"其他",任务清单!$G$3:$G$122,"进行中") | E29: =B29-C29 | F29: =IFERROR(C29/B29,"")
A31: ⚠️ 延期预警（数量）
A32: 当前延期任务数 | B32: =COUNTIF(任务清单!$J$3:$J$122,"⚠️延期")+COUNTIF(任务清单!$G$3:$G$122,"已延期")
A33: → 在「任务清单」按『是否延期』筛选 ⚠️延期 查看明细。

Sheet 说明
A1: 工作进度管理 · 优化说明
A2: 为什么改 | B2: 原表按『日期块』铺开，状态散落在几十个格子里，无法一眼看出完成率/谁拖了/有无延期。
A3: 新结构 | B3: ① 任务清单：一行一个任务，可筛选排序；② 进度看板：自动算完成率/按人/按部门/延期。
A5: 任务清单 · 怎么填 | B5: 日期/部门/负责人/分类/状态都是下拉；工作内容手写；计划完成日建议都填(用于延期判断)。
A6: 状态自动上色 | B6: 已完成=绿 / 进行中=黄 / 未开始=灰 / 已延期=红 / 搁置=蓝灰。选完即变色，进度一眼可见。
A7: 延期自动预警 | B7: 状态非『已完成』且『计划完成日』已过 → 自动标 ⚠️延期，整行淡红。
A8: 进度看板 | B8: 总体完成率(带进度条)、各状态数量、按负责人/部门完成率(带进度条)、延期数——全自动。
A10: 导入 Google Sheets | B10: 文件→导入→上传本xlsx→『替换/新建表格』。下拉、颜色、进度条基本保留；如个别条件格式没跟过来，按本页重设一次即可。
A11: 筛选看单人 | B11: 任务清单选中表头→数据→创建筛选器→按『负责人』筛，即得某人全部任务与进度。

Sheet 选项
A1: 部门 | B1: 负责人 | C1: 分类 | D1: 状态
A2: 日本 | B2: 小裴(财务) | C2: 财务 | D2: 未开始
A3: 樱拓 | B3: 咩咩(贸易) | C3: 贸易 | D3: 进行中
A4: 樱启 | B4: 张姐(供应链) | C4: 供应链 | D4: 已完成
A5: 其他 | B5: 毛毛(小红书) | C5: 小红书 | D5: 已延期
B6: Alice(小红书) | C6: 行政/其他 | D6: 搁置
B7: 柚子(小红书)
B8: 其他
