Workbook

Sheet 计划① 分布总览
A1: 皇后的秘密面膜（Quality1st）· 小红书笔记方向与分布计划（8–11月 / 约122篇 / 双11前 · 不含预算）
A2: 总篇数 | C2: 主力起点(痛点+品类) | E2: 视频占比 | G2: 投放期
A3: 约122篇 | C3: 75% | E3: 约35% | G3: 8–11月·双11前
A5: 表A ｜ 按「起点」× 月份 分布（起点＝这篇要接住正在找什么的人）
A6: 起点 | B6: 8月 | C6: 9月 | D6: 10月 | E6: 11月 | F6: 合计 | G6: 占比 | H6: 主形式
A7: 痛点起点 | B7: 22 | C7: 18 | D7: 8 | E7: 2 | F7: 50 | G7: 41% | H7: 场景视频＋3分钟前后对比
A8: 品类起点 | B8: 16 | C8: 16 | D8: 8 | E8: 2 | F8: 42 | G8: 34% | H8: 选购攻略／合集（7图＋）
A9: 品牌起点 | B9: 4 | C9: 4 | D9: 3 | E9: 2 | F9: 13 | G9: 11% | H9: 分款答疑·黑钻VC100用法
A10: 旅行/代购起点 | B10: 0 | C10: 0 | D10: 0 | E10: 0 | F10: 0 | G10: 0% | H10: 本期不做（会推回日本旅行标签）
A11: 合计 | B11: 46 | C11: 45 | D11: 25 | E11: 6 | F11: 122 | G11: 100% | H11: 痛点+品类=91篇(75%)为重心，也是最缺的内容
A13: 表B ｜ 按「笔记类型 / 形式」分布（团队照此配置内容·不含预算）
A14: 笔记类型 | B14: 形式 | C14: 篇数 | D14: 占比 | E14: 对应起点 | F14: 作用 | G14: 写法要点
A15: 场景种草视频 | B15: 视频 | C15: 43 | D15: 35% | E15: 痛点/品牌用法 | F15: 母婴级信任·爆文引擎 | G15: 真人素颜·3分钟前后同角度对比·先写状态不写品牌
A16: 痛点体验图文 | B16: 图文 | C16: 15 | D16: 12% | E16: 痛点 | F16: 铺量·占搜索长尾 | G16: 状态+真实体感·多图·答案式开头埋长尾词
A17: 选购攻略·合集 | B17: 图文/KOL | C17: 30 | D17: 25% | E17: 品类 | F17: 搜索金矿·高收藏 | G17: 7图以上·按肤质分类表·品牌只作其中一个选项
A18: 品牌答疑·用法 | B18: 图文/视频 | C18: 17 | D18: 14% | E18: 品牌 | F18: 立主角·统一心智 | G18: 分款功效对比表·敷3分钟正确步骤·黑钻VC100主角
A19: 合计 | C19: 122 | D19: 1 | F19: 形式配比：视频约43 · 图文约58 · 攻略合集约30(含腰部KOL约21)
A21: 核心思路（来自你的100篇复盘）：① 视频从10%提到约35%（视频均互动857 vs 图文150）；② 立「黑钻VC100」为主角+统一品牌词（原9款无主角、仅51%提及）；③ 补攻略引擎（原A攻略仅8篇）；④ 淘汰日本杂货代购号，换赛道到毛孔/面膜。详见「③ 写法逻辑与合规」。

Sheet 计划② 选题库
A1: 皇后的秘密面膜 笔记选题库（方向模板·可复制放大）—— 标题为示例方向，团队据此扩写；每个方向可由不同达人各写数篇
A2: # | B2: 起点 | C2: 笔记类型 | D2: 选题方向（标题示例） | E2: 核心搜索/关键词 | F2: 形式 | G2: 建议月 | H2: 合规 | I2: 写法要点
A3: 1 | B3: 痛点 | C3: 场景视频 | D3: 熬夜第二天脸垮了，通勤前3分钟救回来的一步 | E3: 熬夜脸用什么面膜 | F3: 视频 | G3: 8 | H3: 可用 | I3: 真人素颜·3分钟前后同角度对比·金色款·先写状态不写品牌
A4: 2 | B4: 痛点 | C4: 场景视频 | D4: 油皮大毛孔，换季我这样敷更服帖 | E4: 油皮面膜推荐 | F4: 视频 | G4: 8 | H4: 软化 | I4: 细致毛孔/控油=软化·禁「收缩毛孔」·黑色款/黑钻VC100
A5: 3 | B5: 痛点 | C5: 场景视频 | D5: 暗沉没气色，敷完妆前很服帖 | E5: 面膜 妆前 服帖 | F5: 视频 | G5: 9 | H5: 可用 | I5: 妆前场景·服帖/透亮=可用·真人上妆·银色/金色款
A6: 4 | B6: 痛点 | C6: 痛点图文 | D6: 熬夜党的急救面膜，3分钟=1支精华 | E6: 熬夜急救 面膜 | F6: 图文 | G6: 8 | H6: 可用 | I6: 3分钟=1支精华（事实陈述）·真实体验·多图
A7: 5 | B7: 痛点 | C7: 场景视频 | D7: 换季干燥卡粉，妆前敷这片补水 | E7: 换季维稳 面膜 | F7: 视频 | G7: 9 | H7: 可用 | I7: 补水保湿=可用·浅蓝神经酰胺款·妆前对比
A8: 6 | B8: 痛点 | C8: 痛点图文 | D8: 油痘肌闷痘期，我的温和补水护理 | E8: 干敏肌 面膜 | F8: 图文 | G8: 10 | H8: 可用 | I8: 补水/温和=可用·禁「祛痘/修复」·浅蓝款
A9: 7 | B9: 痛点 | C9: 场景视频 | D9: 加班脸色差，早八3分钟贴一片 | E9: 气色差 面膜 | F9: 视频 | G9: 10 | H9: 可用 | I9: 细腻/清爽=可用·场景真实·金色款
A10: 8 | B10: 痛点 | C10: 痛点图文 | D10: 秋冬脸干紧绷，换季补水急救 | E10: 换季 补水 面膜 | F10: 图文 | G10: 10 | H10: 可用 | I10: 补水保湿=可用·真实体感·浅蓝款
A11: 9 | B11: 品类 | C11: 选购攻略 | D11: 日本面膜怎么选不踩雷｜按肤质分 | E11: 日本面膜怎么选 | F11: 合集 | G11: 8 | H11: 可用 | I11: 7图以上·按肤质分类表·皇后只作其中一个选项
A12: 10 | B12: 品类 | C12: 选购攻略 | D12: VC面膜怎么挑，浓度看哪里 | E12: VC面膜怎么选 | F12: 攻略 | G12: 8 | H12: 可用 | I12: 成分科普·VC/烟酰胺客观陈述·黑钻VC100列入
A13: 11 | B13: 品类 | C13: 选购合集 | D13: 敏感肌面膜推荐，避开这几类 | E13: 敏感肌面膜推荐 | F13: 合集 | G13: 9 | H13: 软化 | I13: 『敏感肌也在用』优于『适合敏感肌』·神经酰胺款
A14: 12 | B14: 品类 | C14: 选购合集 | D14: 打工人平价面膜合集，学生党收藏 | E14: 平价面膜 | F14: 合集 | G14: 9 | H14: 可用 | I14: 平价作合集角度·个体不打『超便宜』·清单型
... A23: 26 | B23: 品牌 | C23: 用法视频 | D23: 黑钻VC100早八急救用法，通勤党收藏 | E23: 黑钻VC100 用法 | F23: 视频 | G23: 11 | H23: 可用 | I23: 主角SKU·场景用法·CTA+话题#皇后的秘密面膜
A25: 说明：以上26个方向是「模板起点」，每个方向可由不同达人换角度/肤质/场景各写数篇，扩到约122篇。合规「软化」= 需按第③页规则改措辞后再用；「禁用」词绝不进标题/正文/话题。

Sheet 计划③ 写法与合规
A1: 皇后的秘密面膜 · 每种笔记怎么写 + 写法逻辑 + 合规
A3: 一、五种笔记怎么写（团队照此配置内容）
A4: 1) 场景种草视频（视频·主力43篇）：真人素颜出镜，先讲「我脸现在什么状态」（熬夜脸/大毛孔/暗沉/换季干），敷3分钟做「前后同角度对比」。首图=前后对比或素颜特写。别一上来报品牌。用金色款(妆前提亮)/黑钻VC100(油皮毛孔)/浅蓝款(换季补水)分场景。
A5: 2) 痛点体验图文（图文·15篇）：素人真实口吻「宝宝状态→我怎么敷→真实感受」，多图。正文前3行用答案式开头埋1–2个长尾词（如「熬夜脸用什么面膜」）。讲体感（服帖/清爽/不闷肤），不讲功效承诺。
A6: 3) 选购攻略·合集（图文·30篇·爆文引擎）：7张以上，做「按肤质分类表」，皇后的秘密只作为其中一个选项出现（更可信）。标题=品类长尾词（面膜怎么选/VC面膜怎么选/敏感肌面膜推荐）。这类是搜索金矿+高收藏，参考lululun：选购攻略型均互动1520，是场景种草型的39倍。
A7: 4) 竞品对比测评（图文·17篇）：做「成分·价格对比表」，真实双敷，客观。不贬低竞品、不打「平价/超便宜」。每篇把黑钻VC100立成主角。抢蒂佳婷/3号面膜/爱和纯的比较流量。
A8: 5) 品牌答疑·用法（图文/视频·17篇）：分款功效对比表（金=妆前提亮/黑=控油细致毛孔/浅蓝=神经酰胺换季维稳/银=提亮透亮/黑钻VC100=成分党净透），敷3分钟正确步骤，正品渠道科普（讲哪买正品、不放站外链接）。统一品牌词，立主角SKU。
A10: 二、来自你100篇复盘的6条纠偏（这版必须做到）
A11: ① 提视频比例：视频均互动857 vs 图文150（5.7倍），但原来视频只占10% → 这版提到约35%，痛点场景+3分钟前后对比全部走视频。
A12: ② 立「黑钻VC100」为主角+统一品牌词：原来9款SKU全铺、无主角、仅51%笔记提及品牌、写法有3种 → 所有笔记统一品牌词，黑钻VC100当差异化主角贯穿竞品/品牌起点。
A13: ③ 补「攻略引擎」：原来A攻略只有8篇、「怎么选」进标题仅2次 → 品类攻略/合集提到30篇（参考lululun：7图以上均互动895，是1张图的41倍）。
A14: ④ 淘汰日本杂货代购号、换赛道：原来爆文多是代购号带流量、日本/购物类话题157次≫功效类51次 → 起点换到毛孔/面膜/熬夜，旅行·免税·代购语境本期不做（会把品牌推回「日本旅行」兴趣标签）。
... A23: 分界线：写「我现在是什么状态」可以，写「用了会变成什么」不行。痛点起点全部落在前者，所以能大量铺而不踩线。

Sheet ① 图文KOC投放笔记
A1: 排期 · 投前确认 | H1: 投后 · 基础 | O1: 数据追踪 T+3 | V1: 数据追踪 T+7 | AC1: 数据追踪 T+15 | AJ1: 效率指标（自动） | AO1: 结算 · 转化
A2: 序号 | B2: 状态 | C2: 计划发布日 | D2: 达人名称 | E2: 达人主页链接 | F2: 合作社/MCN | G2: 投放产品 | H2: 实际发布日 | I2: 笔记标题 | J2: 笔记链接 | K2: 图片数 | L2: 品牌词植入 | M2: 话题维护 | N2: 主话题词 | O2: T+3采集日 | P2: 曝光 | Q2: 点赞 | R2: 收藏 | S2: 评论 | T2: 分享 | U2: 证据截图 | V2: T+7采集日 | W2: 曝光 | X2: 点赞 | Y2: 收藏 | Z2: 评论 | AA2: 分享 | AB2: 证据截图 | AC2: T+15采集日 | AD2: 曝光 | AE2: 点赞 | AF2: 收藏 | AG2: 评论 | AH2: 分享 | AI2: 证据截图 | AJ2: 最终互动量 | AK2: 互动率 | AL2: 收藏率 | AM2: CPE互动成本 | AN2: CPM千次曝光 | AO2: 笔记费用(元)
A3: 1 | AJ3: =IF(AD3="","",AE3+AF3+AG3+AH3) | AK3: =IF(OR(AD3="",AD3=0),"",AJ3/AD3) | AL3: =IF(OR(AD3="",AD3=0),"",AF3/AD3) | AM3: =IF(OR(AO3="",AJ3="",AJ3=0),"",AO3/AJ3) | AN3: =IF(OR(AO3="",AD3="",AD3=0),"",AO3/AD3*1000)
A4: 2 | AJ4: =IF(AD4="","",AE4+AF4+AG4+AH4) | AK4: =IF(OR(AD4="",AD4=0),"",AJ4/AD4) | AL4: =IF(OR(AD4="",AD4=0),"",AF4/AD4) | AM4: =IF(OR(AO4="",AJ4="",AJ4=0),"",AO4/AJ4) | AN4: =IF(OR(AO4="",AD4="",AD4=0),"",AO4/AD4*1000)
A5: 3 | AJ5: =IF(AD5="","",AE5+AF5+AG5+AH5) | AK5: =IF(OR(AD5="",AD5=0),"",AJ5/AD5) | AL5: =IF(OR(AD5="",AD5=0),"",AF5/AD5) | AM5: =IF(OR(AO5="",AJ5="",AJ5=0),"",AO5/AJ5) | AN5: =IF(OR(AO5="",AD5="",AD5=0),"",AO5/AD5*1000)
A6: 4 | AJ6: =IF(AD6="","",AE6+AF6+AG6+AH6) | AK6: =IF(OR(AD6="",AD6=0),"",AJ6/AD6) | AL6: =IF(OR(AD6="",AD6=0),"",AF6/AD6) | AM6: =IF(OR(AO6="",AJ6="",AJ6=0),"",AO6/AJ6) | AN6: =IF(OR(AO6="",AD6="",AD6=0),"",AO6/AD6*1000)
A7: 5 | AJ7: =IF(AD7="","",AE7+AF7+AG7+AH7) | AK7: =IF(OR(AD7="",AD7=0),"",AJ7/AD7) | AL7: =IF(OR(AD7="",AD7=0),"",AF7/AD7) | AM7: =IF(OR(AO7="",AJ7="",AJ7=0),"",AO7/AJ7) | AN7: =IF(OR(AO7="",AD7="",AD7=0),"",AO7/AD7*1000)
A8: 6 | AJ8: =IF(AD8="","",AE8+AF8+AG8+AH8) | AK8: =IF(OR(AD8="",AD8=0),"",AJ8/AD8) | AL8: =IF(OR(AD8="",AD8=0),"",AF8/AD8) | AM8: =IF(OR(AO8="",AJ8="",AJ8=0),"",AO8/AJ8) | AN8: =IF(OR(AO8="",AD8="",AD8=0),"",AO8/AD8*1000)
A9: 7 | AJ9: =IF(AD9="","",AE9+AF9+AG9+AH9) | AK9: =IF(OR(AD9="",AD9=0),"",AJ9/AD9) | AL9: =IF(OR(AD9="",AD9=0),"",AF9/AD9) | AM9: =IF(OR(AO9="",AJ9="",AJ9=0),"",AO9/AJ9) | AN9: =IF(OR(AO9="",AD9="",AD9=0),"",AO9/AD9*1000)
A10: 8 | AJ10: =IF(AD10="","",AE10+AF10+AG10+AH10) | AK10: =IF(OR(AD10="",AD10=0),"",AJ10/AD10) | AL10: =IF(OR(AD10="",AD10=0),"",AF10/AD10) | AM10: =IF(OR(AO10="",AJ10="",AJ10=0),"",AO10/AJ10) | AN10: =IF(OR(AO10="",AD10="",AD10=0),"",AO10/AD10*1000)
A11: 9 | AJ11: =IF(AD11="","",AE11+AF11+AG11+AH11) | AK11: =IF(OR(AD11="",AD11=0),"",AJ11/AD11) | AL11: =IF(OR(AD11="",AD11=0),"",AF11/AD11) | AM11: =IF(OR(AO11="",AJ11="",AJ11=0),"",AO11/AJ11) | AN11: =IF(OR(AO11="",AD11="",AD11=0),"",AO11/AD11*1000)
A12: 10 | AJ12: =IF(AD12="","",AE12+AF12+AG12+AH12) | AK12: =IF(OR(AD12="",AD12=0),"",AJ12/AD12) | AL12: =IF(OR(AD12="",AD12=0),"",AF12/AD12) | AM12: =IF(OR(AO12="",AJ12="",AJ12=0),"",AO12/AJ12) | AN12: =IF(OR(AO12="",AD12="",AD12=0),"",AO12/AD12*1000)
A13: 11 | AJ13: =IF(AD13="","",AE13+AF13+AG13+AH13) | AK13: =IF(OR(AD13="",AD13=0),"",AJ13/AD13) | AL13: =IF(OR(AD13="",AD13=0),"",AF13/AD13) | AM13: =IF(OR(AO13="",AJ13="",AJ13=0),"",AO13/AJ13) | AN13: =IF(OR(AO13="",AD13="",AD13=0),"",AO13/AD13*1000)
A14: 12 | AJ14: =IF(AD14="","",AE14+AF14+AG14+AH14) | AK14: =IF(OR(AD14="",AD14=0),"",AJ14/AD14) | AL14: =IF(OR(AD14="",AD14=0),"",AF14/AD14) | AM14: =IF(OR(AO14="",AJ14="",AJ14=0),"",AO14/AJ14) | AN14: =IF(OR(AO14="",AD14="",AD14=0),"",AO14/AD14*1000)
... A42: 40 | AJ42: =IF(AD42="","",AE42+AF42+AG42+AH42) | AK42: =IF(OR(AD42="",AD42=0),"",AJ42/AD42) | AL42: =IF(OR(AD42="",AD42=0),"",AF42/AD42) | AM42: =IF(OR(AO42="",AJ42="",AJ42=0),"",AO42/AJ42) | AN42: =IF(OR(AO42="",AD42="",AD42=0),"",AO42/AD42*1000)

Sheet ② 视频KOC投放笔记
A1: 排期 · 投前确认 | H1: 投后 · 基础 | O1: 数据追踪 T+3 | V1: 数据追踪 T+7 | AC1: 数据追踪 T+15 | AJ1: 效率指标（自动） | AO1: 结算 · 转化
A2: 序号 | B2: 状态 | C2: 计划发布日 | D2: 达人名称 | E2: 达人主页链接 | F2: 合作社/MCN | G2: 投放产品 | H2: 实际发布日 | I2: 笔记标题 | J2: 笔记链接 | K2: 图片数 | L2: 品牌词植入 | M2: 话题维护 | N2: 主话题词 | O2: T+3采集日 | P2: 曝光 | Q2: 点赞 | R2: 收藏 | S2: 评论 | T2: 分享 | U2: 证据截图 | V2: T+7采集日 | W2: 曝光 | X2: 点赞 | Y2: 收藏 | Z2: 评论 | AA2: 分享 | AB2: 证据截图 | AC2: T+15采集日 | AD2: 曝光 | AE2: 点赞 | AF2: 收藏 | AG2: 评论 | AH2: 分享 | AI2: 证据截图 | AJ2: 最终互动量 | AK2: 互动率 | AL2: 收藏率 | AM2: CPE互动成本 | AN2: CPM千次曝光 | AO2: 笔记费用(元)
A3: 1 | AJ3: =IF(AD3="","",AE3+AF3+AG3+AH3) | AK3: =IF(OR(AD3="",AD3=0),"",AJ3/AD3) | AL3: =IF(OR(AD3="",AD3=0),"",AF3/AD3) | AM3: =IF(OR(AO3="",AJ3="",AJ3=0),"",AO3/AJ3) | AN3: =IF(OR(AO3="",AD3="",AD3=0),"",AO3/AD3*1000)
A4: 2 | AJ4: =IF(AD4="","",AE4+AF4+AG4+AH4) | AK4: =IF(OR(AD4="",AD4=0),"",AJ4/AD4) | AL4: =IF(OR(AD4="",AD4=0),"",AF4/AD4) | AM4: =IF(OR(AO4="",AJ4="",AJ4=0),"",AO4/AJ4) | AN4: =IF(OR(AO4="",AD4="",AD4=0),"",AO4/AD4*1000)
A5: 3 | AJ5: =IF(AD5="","",AE5+AF5+AG5+AH5) | AK5: =IF(OR(AD5="",AD5=0),"",AJ5/AD5) | AL5: =IF(OR(AD5="",AD5=0),"",AF5/AD5) | AM5: =IF(OR(AO5="",AJ5="",AJ5=0),"",AO5/AJ5) | AN5: =IF(OR(AO5="",AD5="",AD5=0),"",AO5/AD5*1000)
A6: 4 | AJ6: =IF(AD6="","",AE6+AF6+AG6+AH6) | AK6: =IF(OR(AD6="",AD6=0),"",AJ6/AD6) | AL6: =IF(OR(AD6="",AD6=0),"",AF6/AD6) | AM6: =IF(OR(AO6="",AJ6="",AJ6=0),"",AO6/AJ6) | AN6: =IF(OR(AO6="",AD6="",AD6=0),"",AO6/AD6*1000)
A7: 5 | AJ7: =IF(AD7="","",AE7+AF7+AG7+AH7) | AK7: =IF(OR(AD7="",AD7=0),"",AJ7/AD7) | AL7: =IF(OR(AD7="",AD7=0),"",AF7/AD7) | AM7: =IF(OR(AO7="",AJ7="",AJ7=0),"",AO7/AJ7) | AN7: =IF(OR(AO7="",AD7="",AD7=0),"",AO7/AD7*1000)
A8: 6 | AJ8: =IF(AD8="","",AE8+AF8+AG8+AH8) | AK8: =IF(OR(AD8="",AD8=0),"",AJ8/AD8) | AL8: =IF(OR(AD8="",AD8=0),"",AF8/AD8) | AM8: =IF(OR(AO8="",AJ8="",AJ8=0),"",AO8/AJ8) | AN8: =IF(OR(AO8="",AD8="",AD8=0),"",AO8/AD8*1000)
A9: 7 | AJ9: =IF(AD9="","",AE9+AF9+AG9+AH9) | AK9: =IF(OR(AD9="",AD9=0),"",AJ9/AD9) | AL9: =IF(OR(AD9="",AD9=0),"",AF9/AD9) | AM9: =IF(OR(AO9="",AJ9="",AJ9=0),"",AO9/AJ9) | AN9: =IF(OR(AO9="",AD9="",AD9=0),"",AO9/AD9*1000)
A10: 8 | AJ10: =IF(AD10="","",AE10+AF10+AG10+AH10) | AK10: =IF(OR(AD10="",AD10=0),"",AJ10/AD10) | AL10: =IF(OR(AD10="",AD10=0),"",AF10/AD10) | AM10: =IF(OR(AO10="",AJ10="",AJ10=0),"",AO10/AJ10) | AN10: =IF(OR(AO10="",AD10="",AD10=0),"",AO10/AD10*1000)
A11: 9 | AJ11: =IF(AD11="","",AE11+AF11+AG11+AH11) | AK11: =IF(OR(AD11="",AD11=0),"",AJ11/AD11) | AL11: =IF(OR(AD11="",AD11=0),"",AF11/AD11) | AM11: =IF(OR(AO11="",AJ11="",AJ11=0),"",AO11/AJ11) | AN11: =IF(OR(AO11="",AD11="",AD11=0),"",AO11/AD11*1000)
A12: 10 | AJ12: =IF(AD12="","",AE12+AF12+AG12+AH12) | AK12: =IF(OR(AD12="",AD12=0),"",AJ12/AD12) | AL12: =IF(OR(AD12="",AD12=0),"",AF12/AD12) | AM12: =IF(OR(AO12="",AJ12="",AJ12=0),"",AO12/AJ12) | AN12: =IF(OR(AO12="",AD12="",AD12=0),"",AO12/AD12*1000)
A13: 11 | AJ13: =IF(AD13="","",AE13+AF13+AG13+AH13) | AK13: =IF(OR(AD13="",AD13=0),"",AJ13/AD13) | AL13: =IF(OR(AD13="",AD13=0),"",AF13/AD13) | AM13: =IF(OR(AO13="",AJ13="",AJ13=0),"",AO13/AJ13) | AN13: =IF(OR(AO13="",AD13="",AD13=0),"",AO13/AD13*1000)
A14: 12 | AJ14: =IF(AD14="","",AE14+AF14+AG14+AH14) | AK14: =IF(OR(AD14="",AD14=0),"",AJ14/AD14) | AL14: =IF(OR(AD14="",AD14=0),"",AF14/AD14) | AM14: =IF(OR(AO14="",AJ14="",AJ14=0),"",AO14/AJ14) | AN14: =IF(OR(AO14="",AD14="",AD14=0),"",AO14/AD14*1000)
... A42: 40 | AJ42: =IF(AD42="","",AE42+AF42+AG42+AH42) | AK42: =IF(OR(AD42="",AD42=0),"",AJ42/AD42) | AL42: =IF(OR(AD42="",AD42=0),"",AF42/AD42) | AM42: =IF(OR(AO42="",AJ42="",AJ42=0),"",AO42/AJ42) | AN42: =IF(OR(AO42="",AD42="",AD42=0),"",AO42/AD42*1000)

Sheet ③ 店铺自发笔记
A1: 排期 · 投前确认 | H1: 投后 · 基础 | O1: 数据追踪 T+3 | V1: 数据追踪 T+7 | AC1: 数据追踪 T+15 | AJ1: 效率指标（自动） | AO1: 结算 · 转化
A2: 序号 | B2: 状态 | C2: 计划发布日 | D2: 达人名称 | E2: 达人主页链接 | F2: 合作社/MCN | G2: 投放产品 | H2: 实际发布日 | I2: 笔记标题 | J2: 笔记链接 | K2: 图片数 | L2: 品牌词植入 | M2: 话题维护 | N2: 主话题词 | O2: T+3采集日 | P2: 曝光 | Q2: 点赞 | R2: 收藏 | S2: 评论 | T2: 分享 | U2: 证据截图 | V2: T+7采集日 | W2: 曝光 | X2: 点赞 | Y2: 收藏 | Z2: 评论 | AA2: 分享 | AB2: 证据截图 | AC2: T+15采集日 | AD2: 曝光 | AE2: 点赞 | AF2: 收藏 | AG2: 评论 | AH2: 分享 | AI2: 证据截图 | AJ2: 最终互动量 | AK2: 互动率 | AL2: 收藏率 | AM2: CPE互动成本 | AN2: CPM千次曝光 | AO2: 笔记费用(元)
A3: 1 | AJ3: =IF(AD3="","",AE3+AF3+AG3+AH3) | AK3: =IF(OR(AD3="",AD3=0),"",AJ3/AD3) | AL3: =IF(OR(AD3="",AD3=0),"",AF3/AD3) | AM3: =IF(OR(AO3="",AJ3="",AJ3=0),"",AO3/AJ3) | AN3: =IF(OR(AO3="",AD3="",AD3=0),"",AO3/AD3*1000)
A4: 2 | AJ4: =IF(AD4="","",AE4+AF4+AG4+AH4) | AK4: =IF(OR(AD4="",AD4=0),"",AJ4/AD4) | AL4: =IF(OR(AD4="",AD4=0),"",AF4/AD4) | AM4: =IF(OR(AO4="",AJ4="",AJ4=0),"",AO4/AJ4) | AN4: =IF(OR(AO4="",AD4="",AD4=0),"",AO4/AD4*1000)
A5: 3 | AJ5: =IF(AD5="","",AE5+AF5+AG5+AH5) | AK5: =IF(OR(AD5="",AD5=0),"",AJ5/AD5) | AL5: =IF(OR(AD5="",AD5=0),"",AF5/AD5) | AM5: =IF(OR(AO5="",AJ5="",AJ5=0),"",AO5/AJ5) | AN5: =IF(OR(AO5="",AD5="",AD5=0),"",AO5/AD5*1000)
A6: 4 | AJ6: =IF(AD6="","",AE6+AF6+AG6+AH6) | AK6: =IF(OR(AD6="",AD6=0),"",AJ6/AD6) | AL6: =IF(OR(AD6="",AD6=0),"",AF6/AD6) | AM6: =IF(OR(AO6="",AJ6="",AJ6=0),"",AO6/AJ6) | AN6: =IF(OR(AO6="",AD6="",AD6=0),"",AO6/AD6*1000)
A7: 5 | AJ7: =IF(AD7="","",AE7+AF7+AG7+AH7) | AK7: =IF(OR(AD7="",AD7=0),"",AJ7/AD7) | AL7: =IF(OR(AD7="",AD7=0),"",AF7/AD7) | AM7: =IF(OR(AO7="",AJ7="",AJ7=0),"",AO7/AJ7) | AN7: =IF(OR(AO7="",AD7="",AD7=0),"",AO7/AD7*1000)
A8: 6 | AJ8: =IF(AD8="","",AE8+AF8+AG8+AH8) | AK8: =IF(OR(AD8="",AD8=0),"",AJ8/AD8) | AL8: =IF(OR(AD8="",AD8=0),"",AF8/AD8) | AM8: =IF(OR(AO8="",AJ8="",AJ8=0),"",AO8/AJ8) | AN8: =IF(OR(AO8="",AD8="",AD8=0),"",AO8/AD8*1000)
A9: 7 | AJ9: =IF(AD9="","",AE9+AF9+AG9+AH9) | AK9: =IF(OR(AD9="",AD9=0),"",AJ9/AD9) | AL9: =IF(OR(AD9="",AD9=0),"",AF9/AD9) | AM9: =IF(OR(AO9="",AJ9="",AJ9=0),"",AO9/AJ9) | AN9: =IF(OR(AO9="",AD9="",AD9=0),"",AO9/AD9*1000)
A10: 8 | AJ10: =IF(AD10="","",AE10+AF10+AG10+AH10) | AK10: =IF(OR(AD10="",AD10=0),"",AJ10/AD10) | AL10: =IF(OR(AD10="",AD10=0),"",AF10/AD10) | AM10: =IF(OR(AO10="",AJ10="",AJ10=0),"",AO10/AJ10) | AN10: =IF(OR(AO10="",AD10="",AD10=0),"",AO10/AD10*1000)
A11: 9 | AJ11: =IF(AD11="","",AE11+AF11+AG11+AH11) | AK11: =IF(OR(AD11="",AD11=0),"",AJ11/AD11) | AL11: =IF(OR(AD11="",AD11=0),"",AF11/AD11) | AM11: =IF(OR(AO11="",AJ11="",AJ11=0),"",AO11/AJ11) | AN11: =IF(OR(AO11="",AD11="",AD11=0),"",AO11/AD11*1000)
A12: 10 | AJ12: =IF(AD12="","",AE12+AF12+AG12+AH12) | AK12: =IF(OR(AD12="",AD12=0),"",AJ12/AD12) | AL12: =IF(OR(AD12="",AD12=0),"",AF12/AD12) | AM12: =IF(OR(AO12="",AJ12="",AJ12=0),"",AO12/AJ12) | AN12: =IF(OR(AO12="",AD12="",AD12=0),"",AO12/AD12*1000)
A13: 11 | AJ13: =IF(AD13="","",AE13+AF13+AG13+AH13) | AK13: =IF(OR(AD13="",AD13=0),"",AJ13/AD13) | AL13: =IF(OR(AD13="",AD13=0),"",AF13/AD13) | AM13: =IF(OR(AO13="",AJ13="",AJ13=0),"",AO13/AJ13) | AN13: =IF(OR(AO13="",AD13="",AD13=0),"",AO13/AD13*1000)
A14: 12 | AJ14: =IF(AD14="","",AE14+AF14+AG14+AH14) | AK14: =IF(OR(AD14="",AD14=0),"",AJ14/AD14) | AL14: =IF(OR(AD14="",AD14=0),"",AF14/AD14) | AM14: =IF(OR(AO14="",AJ14="",AJ14=0),"",AO14/AJ14) | AN14: =IF(OR(AO14="",AD14="",AD14=0),"",AO14/AD14*1000)
... A42: 40 | AJ42: =IF(AD42="","",AE42+AF42+AG42+AH42) | AK42: =IF(OR(AD42="",AD42=0),"",AJ42/AD42) | AL42: =IF(OR(AD42="",AD42=0),"",AF42/AD42) | AM42: =IF(OR(AO42="",AJ42="",AJ42=0),"",AO42/AJ42) | AN42: =IF(OR(AO42="",AD42="",AD42=0),"",AO42/AD42*1000)

Sheet ④ 素人笔记·留存追踪
A1: 素人笔记 · 基础 | J1: 发现时基线 | N1: 观测① · 第1个月 | S1: 观测② · 第2个月 | X1: 观测③ · 第3个月 | AC1: 留存结果（自动）
A2: 序号 | B2: 首次发现日 | C2: 素人账号昵称 | D2: 账号链接 | E2: 涉及产品 | F2: 内容形式 | G2: 情感倾向 | H2: 笔记标题 | I2: 笔记链接 | J2: 基线-曝光估 | K2: 基线-点赞 | L2: 基线-收藏 | M2: 基线-评论 | N2: ①观测日 | O2: ①状态 | P2: ①点赞 | Q2: ①收藏 | R2: ①评论 | S2: ②观测日 | T2: ②状态 | U2: ②点赞 | V2: ②收藏 | W2: ②评论 | X2: ③观测日 | Y2: ③状态 | Z2: ③点赞 | AA2: ③收藏 | AB2: ③评论 | AC2: 存活观测数 | AD2: 满3月留存 | AE2: 备注
A3: 1 | AC3: =IF(O3="","",IF(O3="在",1,0)+IF(T3="在",1,0)+IF(Y3="在",1,0)) | AD3: =IF(Y3="在","是",IF(OR(O3="",T3="",Y3=""),"观测中","否"))
A4: 2 | AC4: =IF(O4="","",IF(O4="在",1,0)+IF(T4="在",1,0)+IF(Y4="在",1,0)) | AD4: =IF(Y4="在","是",IF(OR(O4="",T4="",Y4=""),"观测中","否"))
A5: 3 | AC5: =IF(O5="","",IF(O5="在",1,0)+IF(T5="在",1,0)+IF(Y5="在",1,0)) | AD5: =IF(Y5="在","是",IF(OR(O5="",T5="",Y5=""),"观测中","否"))
A6: 4 | AC6: =IF(O6="","",IF(O6="在",1,0)+IF(T6="在",1,0)+IF(Y6="在",1,0)) | AD6: =IF(Y6="在","是",IF(OR(O6="",T6="",Y6=""),"观测中","否"))
A7: 5 | AC7: =IF(O7="","",IF(O7="在",1,0)+IF(T7="在",1,0)+IF(Y7="在",1,0)) | AD7: =IF(Y7="在","是",IF(OR(O7="",T7="",Y7=""),"观测中","否"))
A8: 6 | AC8: =IF(O8="","",IF(O8="在",1,0)+IF(T8="在",1,0)+IF(Y8="在",1,0)) | AD8: =IF(Y8="在","是",IF(OR(O8="",T8="",Y8=""),"观测中","否"))
A9: 7 | AC9: =IF(O9="","",IF(O9="在",1,0)+IF(T9="在",1,0)+IF(Y9="在",1,0)) | AD9: =IF(Y9="在","是",IF(OR(O9="",T9="",Y9=""),"观测中","否"))
A10: 8 | AC10: =IF(O10="","",IF(O10="在",1,0)+IF(T10="在",1,0)+IF(Y10="在",1,0)) | AD10: =IF(Y10="在","是",IF(OR(O10="",T10="",Y10=""),"观测中","否"))
A11: 9 | AC11: =IF(O11="","",IF(O11="在",1,0)+IF(T11="在",1,0)+IF(Y11="在",1,0)) | AD11: =IF(Y11="在","是",IF(OR(O11="",T11="",Y11=""),"观测中","否"))
A12: 10 | AC12: =IF(O12="","",IF(O12="在",1,0)+IF(T12="在",1,0)+IF(Y12="在",1,0)) | AD12: =IF(Y12="在","是",IF(OR(O12="",T12="",Y12=""),"观测中","否"))
A13: 11 | AC13: =IF(O13="","",IF(O13="在",1,0)+IF(T13="在",1,0)+IF(Y13="在",1,0)) | AD13: =IF(Y13="在","是",IF(OR(O13="",T13="",Y13=""),"观测中","否"))
A14: 12 | AC14: =IF(O14="","",IF(O14="在",1,0)+IF(T14="在",1,0)+IF(Y14="在",1,0)) | AD14: =IF(Y14="在","是",IF(OR(O14="",T14="",Y14=""),"观测中","否"))
... A52: 50 | AC52: =IF(O52="","",IF(O52="在",1,0)+IF(T52="在",1,0)+IF(Y52="在",1,0)) | AD52: =IF(Y52="在","是",IF(OR(O52="",T52="",Y52=""),"观测中","否"))

Sheet ⑤ 总览Dashboard
A1: 皇后的秘密 · 面膜(Quality1st代运营) · 笔记投放总览 Dashboard（自动汇总）
A2: 填各记录表后自动更新；如未刷新按 F9 或重开文件。
A4: 图文KOC投放（按产品）
A5: 产品 | B5: 篇数 | C5: 总曝光 | D5: 总互动 | E5: 均互动率 | F5: 总花费 | G5: 均CPE
A6: 黑钻VC100(黑金) | B6: =COUNTIFS('① 图文KOC投放笔记'!$G$3:$G$42,"黑钻VC100(黑金)") | C6: =SUMIFS('① 图文KOC投放笔记'!$AD$3:$AD$42,'① 图文KOC投放笔记'!$G$3:$G$42,"黑钻VC100(黑金)") | D6: =SUMIFS('① 图文KOC投放笔记'!$AJ$3:$AJ$42,'① 图文KOC投放笔记'!$G$3:$G$42,"黑钻VC100(黑金)") | E6: =IFERROR(AVERAGEIFS('① 图文KOC投放笔记'!$AK$3:$AK$42,'① 图文KOC投放笔记'!$G$3:$G$42,"黑钻VC100(黑金)"),"") | F6: =SUMIFS('① 图文KOC投放笔记'!$AO$3:$AO$42,'① 图文KOC投放笔记'!$G$3:$G$42,"黑钻VC100(黑金)") | G6: =IFERROR(AVERAGEIFS('① 图文KOC投放笔记'!$AM$3:$AM$42,'① 图文KOC投放笔记'!$G$3:$G$42,"黑钻VC100(黑金)"),"")
A7: 金色·提亮补水 | B7: =COUNTIFS('① 图文KOC投放笔记'!$G$3:$G$42,"金色·提亮补水") | C7: =SUMIFS('① 图文KOC投放笔记'!$AD$3:$AD$42,'① 图文KOC投放笔记'!$G$3:$G$42,"金色·提亮补水") | D7: =SUMIFS('① 图文KOC投放笔记'!$AJ$3:$AJ$42,'① 图文KOC投放笔记'!$G$3:$G$42,"金色·提亮补水") | E7: =IFERROR(AVERAGEIFS('① 图文KOC投放笔记'!$AK$3:$AK$42,'① 图文KOC投放笔记'!$G$3:$G$42,"金色·提亮补水"),"") | F7: =SUMIFS('① 图文KOC投放笔记'!$AO$3:$AO$42,'① 图文KOC投放笔记'!$G$3:$G$42,"金色·提亮补水") | G7: =IFERROR(AVERAGEIFS('① 图文KOC投放笔记'!$AM$3:$AM$42,'① 图文KOC投放笔记'!$G$3:$G$42,"金色·提亮补水"),"")
A8: 黑银·水光细毛孔 | B8: =COUNTIFS('① 图文KOC投放笔记'!$G$3:$G$42,"黑银·水光细毛孔") | C8: =SUMIFS('① 图文KOC投放笔记'!$AD$3:$AD$42,'① 图文KOC投放笔记'!$G$3:$G$42,"黑银·水光细毛孔") | D8: =SUMIFS('① 图文KOC投放笔记'!$AJ$3:$AJ$42,'① 图文KOC投放笔记'!$G$3:$G$42,"黑银·水光细毛孔") | E8: =IFERROR(AVERAGEIFS('① 图文KOC投放笔记'!$AK$3:$AK$42,'① 图文KOC投放笔记'!$G$3:$G$42,"黑银·水光细毛孔"),"") | F8: =SUMIFS('① 图文KOC投放笔记'!$AO$3:$AO$42,'① 图文KOC投放笔记'!$G$3:$G$42,"黑银·水光细毛孔") | G8: =IFERROR(AVERAGEIFS('① 图文KOC投放笔记'!$AM$3:$AM$42,'① 图文KOC投放笔记'!$G$3:$G$42,"黑银·水光细毛孔"),"")
A9: 深蓝·维稳补水 | B9: =COUNTIFS('① 图文KOC投放笔记'!$G$3:$G$42,"深蓝·维稳补水") | C9: =SUMIFS('① 图文KOC投放笔记'!$AD$3:$AD$42,'① 图文KOC投放笔记'!$G$3:$G$42,"深蓝·维稳补水") | D9: =SUMIFS('① 图文KOC投放笔记'!$AJ$3:$AJ$42,'① 图文KOC投放笔记'!$G$3:$G$42,"深蓝·维稳补水") | E9: =IFERROR(AVERAGEIFS('① 图文KOC投放笔记'!$AK$3:$AK$42,'① 图文KOC投放笔记'!$G$3:$G$42,"深蓝·维稳补水"),"") | F9: =SUMIFS('① 图文KOC投放笔记'!$AO$3:$AO$42,'① 图文KOC投放笔记'!$G$3:$G$42,"深蓝·维稳补水") | G9: =IFERROR(AVERAGEIFS('① 图文KOC投放笔记'!$AM$3:$AM$42,'① 图文KOC投放笔记'!$G$3:$G$42,"深蓝·维稳补水"),"")
A10: 银色·提亮 | B10: =COUNTIFS('① 图文KOC投放笔记'!$G$3:$G$42,"银色·提亮") | C10: =SUMIFS('① 图文KOC投放笔记'!$AD$3:$AD$42,'① 图文KOC投放笔记'!$G$3:$G$42,"银色·提亮") | D10: =SUMIFS('① 图文KOC投放笔记'!$AJ$3:$AJ$42,'① 图文KOC投放笔记'!$G$3:$G$42,"银色·提亮") | E10: =IFERROR(AVERAGEIFS('① 图文KOC投放笔记'!$AK$3:$AK$42,'① 图文KOC投放笔记'!$G$3:$G$42,"银色·提亮"),"") | F10: =SUMIFS('① 图文KOC投放笔记'!$AO$3:$AO$42,'① 图文KOC投放笔记'!$G$3:$G$42,"银色·提亮") | G10: =IFERROR(AVERAGEIFS('① 图文KOC投放笔记'!$AM$3:$AM$42,'① 图文KOC投放笔记'!$G$3:$G$42,"银色·提亮"),"")
A11: （其他/新品） | B11: =COUNTIFS('① 图文KOC投放笔记'!$G$3:$G$42,"（其他/新品）") | C11: =SUMIFS('① 图文KOC投放笔记'!$AD$3:$AD$42,'① 图文KOC投放笔记'!$G$3:$G$42,"（其他/新品）") | D11: =SUMIFS('① 图文KOC投放笔记'!$AJ$3:$AJ$42,'① 图文KOC投放笔记'!$G$3:$G$42,"（其他/新品）") | E11: =IFERROR(AVERAGEIFS('① 图文KOC投放笔记'!$AK$3:$AK$42,'① 图文KOC投放笔记'!$G$3:$G$42,"（其他/新品）"),"") | F11: =SUMIFS('① 图文KOC投放笔记'!$AO$3:$AO$42,'① 图文KOC投放笔记'!$G$3:$G$42,"（其他/新品）") | G11: =IFERROR(AVERAGEIFS('① 图文KOC投放笔记'!$AM$3:$AM$42,'① 图文KOC投放笔记'!$G$3:$G$42,"（其他/新品）"),"")
A13: 视频KOC投放（按产品）
A14: 产品 | B14: 篇数 | C14: 总曝光 | D14: 总互动 | E14: 均互动率 | F14: 总花费 | G14: 均CPE
A15: 黑钻VC100(黑金) | B15: =COUNTIFS('② 视频KOC投放笔记'!$I$3:$I$42,"黑钻VC100(黑金)") | C15: =SUMIFS('② 视频KOC投放笔记'!$AK$3:$AK$42,'② 视频KOC投放笔记'!$I$3:$I$42,"黑钻VC100(黑金)") | D15: =SUMIFS('② 视频KOC投放笔记'!$AQ$3:$AQ$42,'② 视频KOC投放笔记'!$I$3:$I$42,"黑钻VC100(黑金)") | E15: =IFERROR(AVERAGEIFS('② 视频KOC投放笔记'!$AR$3:$AR$42,'② 视频KOC投放笔记'!$I$3:$I$42,"黑钻VC100(黑金)"),"") | F15: =SUMIFS('② 视频KOC投放笔记'!$AV$3:$AV$42,'② 视频KOC投放笔记'!$I$3:$I$42,"黑钻VC100(黑金)") | G15: =IFERROR(AVERAGEIFS('② 视频KOC投放笔记'!$AT$3:$AT$42,'② 视频KOC投放笔记'!$I$3:$I$42,"黑钻VC100(黑金)"),"")
A16: 金色·提亮补水 | B16: =COUNTIFS('② 视频KOC投放笔记'!$I$3:$I$42,"金色·提亮补水") | C16: =SUMIFS('② 视频KOC投放笔记'!$AK$3:$AK$42,'② 视频KOC投放笔记'!$I$3:$I$42,"金色·提亮补水") | D16: =SUMIFS('② 视频KOC投放笔记'!$AQ$3:$AQ$42,'② 视频KOC投放笔记'!$I$3:$I$42,"金色·提亮补水") | E16: =IFERROR(AVERAGEIFS('② 视频KOC投放笔记'!$AR$3:$AR$42,'② 视频KOC投放笔记'!$I$3:$I$42,"金色·提亮补水"),"") | F16: =SUMIFS('② 视频KOC投放笔记'!$AV$3:$AV$42,'② 视频KOC投放笔记'!$I$3:$I$42,"金色·提亮补水") | G16: =IFERROR(AVERAGEIFS('② 视频KOC投放笔记'!$AT$3:$AT$42,'② 视频KOC投放笔记'!$I$3:$I$42,"金色·提亮补水"),"")
A17: 黑银·水光细毛孔 | B17: =COUNTIFS('② 视频KOC投放笔记'!$I$3:$I$42,"黑银·水光细毛孔") | C17: =SUMIFS('② 视频KOC投放笔记'!$AK$3:$AK$42,'② 视频KOC投放笔记'!$I$3:$I$42,"黑银·水光细毛孔") | D17: =SUMIFS('② 视频KOC投放笔记'!$AQ$3:$AQ$42,'② 视频KOC投放笔记'!$I$3:$I$42,"黑银·水光细毛孔") | E17: =IFERROR(AVERAGEIFS('② 视频KOC投放笔记'!$AR$3:$AR$42,'② 视频KOC投放笔记'!$I$3:$I$42,"黑银·水光细毛孔"),"") | F17: =SUMIFS('② 视频KOC投放笔记'!$AV$3:$AV$42,'② 视频KOC投放笔记'!$I$3:$I$42,"黑银·水光细毛孔") | G17: =IFERROR(AVERAGEIFS('② 视频KOC投放笔记'!$AT$3:$AT$42,'② 视频KOC投放笔记'!$I$3:$I$42,"黑银·水光细毛孔"),"")
A18: 深蓝·维稳补水 | B18: =COUNTIFS('② 视频KOC投放笔记'!$I$3:$I$42,"深蓝·维稳补水") | C18: =SUMIFS('② 视频KOC投放笔记'!$AK$3:$AK$42,'② 视频KOC投放笔记'!$I$3:$I$42,"深蓝·维稳补水") | D18: =SUMIFS('② 视频KOC投放笔记'!$AQ$3:$AQ$42,'② 视频KOC投放笔记'!$I$3:$I$42,"深蓝·维稳补水") | E18: =IFERROR(AVERAGEIFS('② 视频KOC投放笔记'!$AR$3:$AR$42,'② 视频KOC投放笔记'!$I$3:$I$42,"深蓝·维稳补水"),"") | F18: =SUMIFS('② 视频KOC投放笔记'!$AV$3:$AV$42,'② 视频KOC投放笔记'!$I$3:$I$42,"深蓝·维稳补水") | G18: =IFERROR(AVERAGEIFS('② 视频KOC投放笔记'!$AT$3:$AT$42,'② 视频KOC投放笔记'!$I$3:$I$42,"深蓝·维稳补水"),"")
A19: 银色·提亮 | B19: =COUNTIFS('② 视频KOC投放笔记'!$I$3:$I$42,"银色·提亮") | C19: =SUMIFS('② 视频KOC投放笔记'!$AK$3:$AK$42,'② 视频KOC投放笔记'!$I$3:$I$42,"银色·提亮") | D19: =SUMIFS('② 视频KOC投放笔记'!$AQ$3:$AQ$42,'② 视频KOC投放笔记'!$I$3:$I$42,"银色·提亮") | E19: =IFERROR(AVERAGEIFS('② 视频KOC投放笔记'!$AR$3:$AR$42,'② 视频KOC投放笔记'!$I$3:$I$42,"银色·提亮"),"") | F19: =SUMIFS('② 视频KOC投放笔记'!$AV$3:$AV$42,'② 视频KOC投放笔记'!$I$3:$I$42,"银色·提亮") | G19: =IFERROR(AVERAGEIFS('② 视频KOC投放笔记'!$AT$3:$AT$42,'② 视频KOC投放笔记'!$I$3:$I$42,"银色·提亮"),"")
A20: （其他/新品） | B20: =COUNTIFS('② 视频KOC投放笔记'!$I$3:$I$42,"（其他/新品）") | C20: =SUMIFS('② 视频KOC投放笔记'!$AK$3:$AK$42,'② 视频KOC投放笔记'!$I$3:$I$42,"（其他/新品）") | D20: =SUMIFS('② 视频KOC投放笔记'!$AQ$3:$AQ$42,'② 视频KOC投放笔记'!$I$3:$I$42,"（其他/新品）") | E20: =IFERROR(AVERAGEIFS('② 视频KOC投放笔记'!$AR$3:$AR$42,'② 视频KOC投放笔记'!$I$3:$I$42,"（其他/新品）"),"") | F20: =SUMIFS('② 视频KOC投放笔记'!$AV$3:$AV$42,'② 视频KOC投放笔记'!$I$3:$I$42,"（其他/新品）") | G20: =IFERROR(AVERAGEIFS('② 视频KOC投放笔记'!$AT$3:$AT$42,'② 视频KOC投放笔记'!$I$3:$I$42,"（其他/新品）"),"")
A22: 店铺自发（按产品）
A23: 产品 | B23: 篇数 | C23: 总曝光 | D23: 总互动 | E23: 均互动率
A24: 黑钻VC100(黑金) | B24: =COUNTIFS('③ 店铺自发笔记'!$E$3:$E$42,"黑钻VC100(黑金)") | C24: =SUMIFS('③ 店铺自发笔记'!$AF$3:$AF$42,'③ 店铺自发笔记'!$E$3:$E$42,"黑钻VC100(黑金)") | D24: =SUMIFS('③ 店铺自发笔记'!$AL$3:$AL$42,'③ 店铺自发笔记'!$E$3:$E$42,"黑钻VC100(黑金)") | E24: =IFERROR(AVERAGEIFS('③ 店铺自发笔记'!$AM$3:$AM$42,'③ 店铺自发笔记'!$E$3:$E$42,"黑钻VC100(黑金)"),"")
A25: 金色·提亮补水 | B25: =COUNTIFS('③ 店铺自发笔记'!$E$3:$E$42,"金色·提亮补水") | C25: =SUMIFS('③ 店铺自发笔记'!$AF$3:$AF$42,'③ 店铺自发笔记'!$E$3:$E$42,"金色·提亮补水") | D25: =SUMIFS('③ 店铺自发笔记'!$AL$3:$AL$42,'③ 店铺自发笔记'!$E$3:$E$42,"金色·提亮补水") | E25: =IFERROR(AVERAGEIFS('③ 店铺自发笔记'!$AM$3:$AM$42,'③ 店铺自发笔记'!$E$3:$E$42,"金色·提亮补水"),"")
A26: 黑银·水光细毛孔 | B26: =COUNTIFS('③ 店铺自发笔记'!$E$3:$E$42,"黑银·水光细毛孔") | C26: =SUMIFS('③ 店铺自发笔记'!$AF$3:$AF$42,'③ 店铺自发笔记'!$E$3:$E$42,"黑银·水光细毛孔") | D26: =SUMIFS('③ 店铺自发笔记'!$AL$3:$AL$42,'③ 店铺自发笔记'!$E$3:$E$42,"黑银·水光细毛孔") | E26: =IFERROR(AVERAGEIFS('③ 店铺自发笔记'!$AM$3:$AM$42,'③ 店铺自发笔记'!$E$3:$E$42,"黑银·水光细毛孔"),"")
A27: 深蓝·维稳补水 | B27: =COUNTIFS('③ 店铺自发笔记'!$E$3:$E$42,"深蓝·维稳补水") | C27: =SUMIFS('③ 店铺自发笔记'!$AF$3:$AF$42,'③ 店铺自发笔记'!$E$3:$E$42,"深蓝·维稳补水") | D27: =SUMIFS('③ 店铺自发笔记'!$AL$3:$AL$42,'③ 店铺自发笔记'!$E$3:$E$42,"深蓝·维稳补水") | E27: =IFERROR(AVERAGEIFS('③ 店铺自发笔记'!$AM$3:$AM$42,'③ 店铺自发笔记'!$E$3:$E$42,"深蓝·维稳补水"),"")
A28: 银色·提亮 | B28: =COUNTIFS('③ 店铺自发笔记'!$E$3:$E$42,"银色·提亮") | C28: =SUMIFS('③ 店铺自发笔记'!$AF$3:$AF$42,'③ 店铺自发笔记'!$E$3:$E$42,"银色·提亮") | D28: =SUMIFS('③ 店铺自发笔记'!$AL$3:$AL$42,'③ 店铺自发笔记'!$E$3:$E$42,"银色·提亮") | E28: =IFERROR(AVERAGEIFS('③ 店铺自发笔记'!$AM$3:$AM$42,'③ 店铺自发笔记'!$E$3:$E$42,"银色·提亮"),"")
A29: （其他/新品） | B29: =COUNTIFS('③ 店铺自发笔记'!$E$3:$E$42,"（其他/新品）") | C29: =SUMIFS('③ 店铺自发笔记'!$AF$3:$AF$42,'③ 店铺自发笔记'!$E$3:$E$42,"（其他/新品）") | D29: =SUMIFS('③ 店铺自发笔记'!$AL$3:$AL$42,'③ 店铺自发笔记'!$E$3:$E$42,"（其他/新品）") | E29: =IFERROR(AVERAGEIFS('③ 店铺自发笔记'!$AM$3:$AM$42,'③ 店铺自发笔记'!$E$3:$E$42,"（其他/新品）"),"")
A31: 素人笔记 · 留存概览
A32: 留存/口碑 | B32: 数量
A33: 满3月留存=是 | B33: =COUNTIFS('④ 素人笔记·留存追踪'!$AD$3:$AD$52,"是")
A34: 满3月留存=否 | B34: =COUNTIFS('④ 素人笔记·留存追踪'!$AD$3:$AD$52,"否")
A35: 观测中 | B35: =COUNTIFS('④ 素人笔记·留存追踪'!$AD$3:$AD$52,"观测中")
A36: 口碑·正面 | B36: =COUNTIFS('④ 素人笔记·留存追踪'!$G$3:$G$52,"正面")
A37: 口碑·中性 | B37: =COUNTIFS('④ 素人笔记·留存追踪'!$G$3:$G$52,"中性")
A38: 口碑·负面 | B38: =COUNTIFS('④ 素人笔记·留存追踪'!$G$3:$G$52,"负面")

Sheet ⑥ 填写说明
A1: 皇后的秘密 · 面膜(Quality1st代运营) · 笔记数据收集表 · 填写说明
A2: 浅黄底 单元格 | B2: 人工填写（输入项）
A3: 浅灰底 单元格 | B3: 自动公式，勿手改（发布月/互动量/互动率/收藏率/CPE/CPM/留存）
A4: 下拉列表 | B4: 状态·产品·类型·合规审核·结算·留存状态等为下拉，选项在「选项」页维护
A6: ① 图文KOC投放笔记 | B6: 付费投放的图文KOC/达人笔记：投前审核→发布→T+3/7/15三轮采数→自动效率。
A7: ② 视频KOC投放笔记 | B7: 付费投放的视频KOC/达人笔记：结构同上，媒体字段为视频时长。
A8: ③ 店铺自发笔记 | B8: 自家蓝V/店铺号发布：无达人费用，重合规与自然数据表现。
A9: ④ 素人笔记·留存追踪 | B9: 素人自发提及品牌的笔记：每月观测1次、连观3个月，看『留存时长』与口碑。
A10: —— 留存状态 | B10: 在=仍可见 / 已删除 / 限流(搜不到) / 改为无关；『满3月留存』自动判定。
A11: ⑤ 总览Dashboard | B11: 各表按产品自动汇总篇数·曝光·互动·互动率·花费·CPE + 素人留存概览。
A13: ⚠️ 合规红线 | B13: 化妆品红线：美白/焕白/去黄/淡斑/抗老/A醇/视黄醇/修复屏障/祛痘/医美/院线/极限词 → 改用提亮/透亮/水润/细致毛孔；小红书禁站外硬导流。

Sheet 选项
A1: 状态 | B1: 达人层级 | C1: 内部对接人 | D1: 笔记类型 | E1: 内容形式 | F1: 合规审核 | G1: 审核人 | H1: 是否 | I1: 话题维护 | J1: 结算状态 | K1: 情感倾向 | L1: 留存状态 | M1: 投放产品
A2: 排期 | B2: 头部KOL | C2: （填成员名） | D2: A·选购攻略 | E2: 图文 | F2: 待审 | G2: （填成员名） | H2: 是 | I2: 已维护 | J2: 未付 | K2: 正面 | L2: 在 | M2: 黑钻VC100(黑金)
A3: 待审稿 | B3: 腰部 | C3: 曹 | D3: B·测评回购 | E3: 视频 | F3: ✅通过 | G3: 曹 | H3: 否 | I3: 未维护 | J3: 已付 | K3: 中性 | L3: 已删除 | M3: 金色·提亮补水
A4: 已投 | B4: 尾部 | C4: 成员A | D4: C·场景种草 | F4: ⚠️需改 | G4: 成员A | I4: 不适用 | J4: 部分付 | K4: 负面 | L4: 限流 | M4: 黑银·水光细毛孔
A5: 追踪中 | B5: KOC | C5: 成员B | D5: D·开箱vlog | F5: ❌驳回 | L5: 改为无关 | M5: 深蓝·维稳补水
A6: 已结案 | D6: E·比价囤货 | M6: 银色·提亮
M7: （其他/新品）
